.gitignore
LICENSE.txt
MANIFEST.in
README.rst
pyproject.toml
requirements.txt
setup.py
toppy/__init__.py
toppy/abc.py
toppy/client.py
toppy/cog.py
toppy/errors.py
toppy/http.py
toppy/models.py
toppy/py.typed
toppy/utils.py
toppy/webhook/__init__.py
toppy/webhook/cache.py
toppy/webhook/payload.py
toppy_python.egg-info/PKG-INFO
toppy_python.egg-info/SOURCES.txt
toppy_python.egg-info/dependency_links.txt
toppy_python.egg-info/requires.txt
toppy_python.egg-info/top_level.txt