Metadata-Version: 2.1
Name: toppy-python
Version: 2.0.1
Summary: A simple API wrapper for Discord Bot List, DiscordBotsGG, and Top.gg
Author: The Master
License: MIT
Project-URL: Documentation, https://toppy-python.readthedocs.io/en/latest/
Project-URL: Github, https://github.com/chawkk6404/toppy
Classifier: Development Status :: 5 - Production/Stable
Classifier: License :: OSI Approved :: MIT License
Classifier: Intended Audience :: Developers
Classifier: Natural Language :: English
Classifier: Operating System :: OS Independent
Classifier: Programming Language :: Python :: 3.8
Classifier: Programming Language :: Python :: 3.9
Classifier: Programming Language :: Python :: 3.10
Classifier: Topic :: Internet
Classifier: Topic :: Software Development :: Libraries
Classifier: Topic :: Software Development :: Libraries :: Python Modules
Classifier: Topic :: Utilities
Classifier: Typing :: Typed
Requires-Python: >=3.8.0
Provides-Extra: cache
License-File: LICENSE.txt
